sekaibot/py.typed
sekaibot/adapter/cqhttp/__init__.py
sekaibot/adapter/cqhttp/config.py
sekaibot/adapter/cqhttp/event.py
sekaibot/adapter/cqhttp/exceptions.py
sekaibot/adapter/cqhttp/message.py
sekaibot_adapter_cqhttp-0.1.3.dist-info/METADATA
sekaibot_adapter_cqhttp-0.1.3.dist-info/WHEEL
sekaibot_adapter_cqhttp-0.1.3.dist-info/RECORD
